README.rst
setup.py
mimes/__init__.py
mimes.egg-info/PKG-INFO
mimes.egg-info/SOURCES.txt
mimes.egg-info/dependency_links.txt
mimes.egg-info/requires.txt
mimes.egg-info/top_level.txt