Metadata-Version: 1.0
Name: mimes
Version: 0.3
Summary: Parses mimetype-strings (RFC 1049, 2045, 2047 and 2231) and allows comparing these.
Home-page: http://github.com/mbr/mimetypes
Author: Marc Brinkmann
Author-email: git@marcbrinkmann.de
License: MIT
Platform: UNKNOWN
